aiodo/__init__.py
aiodo/config.py
aiodo/core.py
aiodo/dummy.py
aiodo/network.py
aiodo/registry.py
aiodo-0.1.0.dist-info/METADATA
aiodo-0.1.0.dist-info/entry_points.txt
aiodo-0.1.0.dist-info/WHEEL
aiodo-0.1.0.dist-info/RECORD
